<?xml version="1.0" ?>
<TEXT ID="1015">
	<TITLE>Belmopan</TITLE>
	<PARAGRAPH ID="1">
		<REFERENCE ID="1" SEMCAT="city" SYNCAT="np-subj">
			<ORIGINAL-REFEX>
				<REFEX CASE="plain" EMPHATIC="no" HEAD="nominal" TYPE="name">Belmopan</REFEX>
			</ORIGINAL-REFEX>
		</REFERENCE>
		<STRING>, estimated population 12,300, is the capital of Belize.</STRING>
	</PARAGRAPH>
	<PARAGRAPH ID="2">
		<REFERENCE ID="2" SEMCAT="city" SYNCAT="np-subj">
			<ORIGINAL-REFEX>
				<REFEX CASE="plain" EMPHATIC="no" HEAD="nominal" TYPE="name">Belmopan</REFEX>
			</ORIGINAL-REFEX>
		</REFERENCE>
		<STRING> is located at 17°15'N,88°46'W, at an altitude of 76 meters (250 ft) above sea level. </STRING>
		<REFERENCE ID="3" SEMCAT="city" SYNCAT="np-subj">
			<ORIGINAL-REFEX>
				<REFEX CASE="plain" EMPHATIC="no" HEAD="nominal" TYPE="name">Belmopan</REFEX>
			</ORIGINAL-REFEX>
		</REFERENCE>
		<STRING> was constructed just to the east of Belize River, 80 km (50 miles) inland from the former capital, the port of Belize City, after that city's near destruction by a hurricane in 1961. The government was moved to </STRING>
		<REFERENCE ID="4" SEMCAT="city" SYNCAT="np-obj">
			<ORIGINAL-REFEX>
				<REFEX CASE="plain" EMPHATIC="no" HEAD="nominal" TYPE="name">Belmopan</REFEX>
			</ORIGINAL-REFEX>
		</REFERENCE>
		<STRING> in 1970. The National Assembly Building is designed to resemble a Pre-Columbian Maya temple. </STRING>
		<REFERENCE ID="5" SEMCAT="city" SYNCAT="np-subj">
			<ORIGINAL-REFEX>
				<REFEX CASE="plain" EMPHATIC="no" HEAD="nominal" TYPE="name">Belmopan</REFEX>
			</ORIGINAL-REFEX>
		</REFERENCE>
		<STRING> is located off of the Hummingbird Highway, one of the most picturesque highways in all of Central America. </STRING>
		<REFERENCE ID="6" SEMCAT="city" SYNCAT="np-subj">
			<ORIGINAL-REFEX>
				<REFEX CASE="plain" EMPHATIC="no" HEAD="nominal" TYPE="name">Belmopan</REFEX>
			</ORIGINAL-REFEX>
		</REFERENCE>
		<STRING> is one of the world's smaller capital cities.</STRING>
	</PARAGRAPH>
</TEXT>
