<?xml version="1.0" ?>
<TEXT ID="1281">
	<TITLE>Guinea</TITLE>
	<PARAGRAPH ID="1">
		<REFERENCE ID="1" SEMCAT="country" SYNCAT="np-subj">
			<ORIGINAL-REFEX>
				<REFEX CASE="plain" EMPHATIC="no" HEAD="nominal" TYPE="name">Guinea</REFEX>
			</ORIGINAL-REFEX>
		</REFERENCE>
		<STRING>, officially the Republic of Guinea (French: République de Guinée), is a nation in West Africa, formerly known as French Guinea. </STRING>
		<REFERENCE ID="2" SEMCAT="country" SYNCAT="np-subj">
			<ORIGINAL-REFEX>
				<REFEX CASE="nominative" EMPHATIC="no" HEAD="pronoun" TYPE="pronoun">It</REFEX>
			</ORIGINAL-REFEX>
		</REFERENCE>
		<STRING> borders Guinea-Bissau and Senegal on the north, Mali on the north and north-east, the Côte d'Ivoire on the south-east, Liberia on the south, and Sierra Leone on the west. </STRING>
		<REFERENCE ID="3" SEMCAT="country" SYNCAT="subj-det">
			<ORIGINAL-REFEX>
				<REFEX CASE="genitive" EMPHATIC="no" HEAD="pronoun" TYPE="pronoun">Its</REFEX>
			</ORIGINAL-REFEX>
		</REFERENCE>
		<STRING> territory encompasses the water source for the Niger, Senegal, and Gambia rivers, with a coastline facing the Atlantic Ocean. The name Guinea (geographically assigned to most of Africa's west coast, south of the Sahara desert and north of the Gulf of Guinea) originates from Berber and roughly translates into 'land of the blacks.' </STRING>
		<REFERENCE ID="4" SEMCAT="country" SYNCAT="np-subj">
			<ORIGINAL-REFEX>
				<REFEX CASE="nominative" EMPHATIC="no" HEAD="pronoun" TYPE="pronoun">It</REFEX>
			</ORIGINAL-REFEX>
		</REFERENCE>
		<STRING> is sometimes called Guinea-Conakry per </STRING>
		<REFERENCE ID="5" SEMCAT="country" SYNCAT="subj-det">
			<ORIGINAL-REFEX>
				<REFEX CASE="genitive" EMPHATIC="no" HEAD="pronoun" TYPE="pronoun">its</REFEX>
			</ORIGINAL-REFEX>
		</REFERENCE>
		<STRING> capital to differentiate </STRING>
		<REFERENCE ID="6" SEMCAT="country" SYNCAT="np-subj">
			<ORIGINAL-REFEX>
				<REFEX CASE="nominative" EMPHATIC="no" HEAD="pronoun" TYPE="pronoun">it</REFEX>
			</ORIGINAL-REFEX>
		</REFERENCE>
		<STRING> from the neighboring Guinea-Bissau (whose capital is Bissau).</STRING>
	</PARAGRAPH>
</TEXT>
