<?xml version="1.0" ?>
<TEXT ID="1555">
	<TITLE>Henry Dunant</TITLE>
	<PARAGRAPH ID="1">
		<REFERENCE ID="1" SEMCAT="person" SYNCAT="np-subj">
			<ORIGINAL-REFEX>
				<REFEX CASE="plain" EMPHATIC="no" HEAD="nominal" TYPE="name">Jean Henri Dunant</REFEX>
			</ORIGINAL-REFEX>
		</REFERENCE>
		<STRING> (May 8, 1828 in Geneva - October 30, 1910 in Heiden), also known as Henry Dunant or Henri Dunant, was a Swiss businessman and social activist. During a business trip in 1859, </STRING>
		<REFERENCE ID="2" SEMCAT="person" SYNCAT="np-subj">
			<ORIGINAL-REFEX>
				<REFEX CASE="nominative" EMPHATIC="no" HEAD="pronoun" TYPE="pronoun">he</REFEX>
			</ORIGINAL-REFEX>
		</REFERENCE>
		<STRING> was witness to the aftermath of the Battle of Solferino in modern day Italy. </STRING>
		<REFERENCE ID="3" SEMCAT="person" SYNCAT="np-subj">
			<ORIGINAL-REFEX>
				<REFEX CASE="nominative" EMPHATIC="no" HEAD="pronoun" TYPE="pronoun">He</REFEX>
			</ORIGINAL-REFEX>
		</REFERENCE>
		<STRING> recorded </STRING>
		<REFERENCE ID="4" SEMCAT="person" SYNCAT="subj-det">
			<ORIGINAL-REFEX>
				<REFEX CASE="genitive" EMPHATIC="no" HEAD="pronoun" TYPE="pronoun">his</REFEX>
			</ORIGINAL-REFEX>
		</REFERENCE>
		<STRING> memories and experiences in the book &quot;A Memory of Solferino&quot; which became the inspiration for the creation of the International Committee of the Red Cross (ICRC). The 1864 Geneva Convention was based on </STRING>
		<REFERENCE ID="5" SEMCAT="person" SYNCAT="subj-det">
			<ORIGINAL-REFEX>
				<REFEX CASE="genitive" EMPHATIC="no" HEAD="nominal" TYPE="name">Dunant's</REFEX>
			</ORIGINAL-REFEX>
		</REFERENCE>
		<STRING> ideas and in 1901 </STRING>
		<REFERENCE ID="6" SEMCAT="person" SYNCAT="np-subj">
			<ORIGINAL-REFEX>
				<REFEX CASE="nominative" EMPHATIC="no" HEAD="pronoun" TYPE="pronoun">he</REFEX>
			</ORIGINAL-REFEX>
		</REFERENCE>
		<STRING> received the first Nobel Peace Prize together with Frédéric Passy.</STRING>
	</PARAGRAPH>
</TEXT>
