<?xml version="1.0" ?>
<TEXT ID="283">
	<TITLE>Lenin Peak</TITLE>
	<PARAGRAPH ID="1">
		<REFERENCE ID="1" SEMCAT="mountain" SYNCAT="np-subj">
			<ORIGINAL-REFEX>
				<REFEX CASE="plain" EMPHATIC="no" HEAD="nominal" TYPE="name">Lenin Peak</REFEX>
			</ORIGINAL-REFEX>
		</REFERENCE>
		<STRING>, known as Mount Kaufmann until 1928, is the highest mountain in the Trans-Alay Range of Central Asia and the second highest peak in the Pamir Mountains, exceeded only by Ismail Samani Peak (7,495m). </STRING>
		<REFERENCE ID="2" SEMCAT="mountain" SYNCAT="np-subj">
			<ORIGINAL-REFEX>
				<REFEX CASE="nominative" EMPHATIC="no" HEAD="pronoun" TYPE="pronoun">It</REFEX>
			</ORIGINAL-REFEX>
		</REFERENCE>
		<STRING> stands on the border of Tajikistan and Kyrgyzstan; </STRING>
		<REFERENCE ID="3" SEMCAT="mountain" SYNCAT="np-subj">
			<ORIGINAL-REFEX>
				<REFEX CASE="nominative" EMPHATIC="no" HEAD="pronoun" TYPE="pronoun">it</REFEX>
			</ORIGINAL-REFEX>
		</REFERENCE>
		<STRING> is the second-highest point of both countries. </STRING>
		<REFERENCE ID="4" SEMCAT="mountain" SYNCAT="np-subj">
			<ORIGINAL-REFEX>
				<REFEX CASE="nominative" EMPHATIC="no" HEAD="pronoun" TYPE="pronoun">It</REFEX>
			</ORIGINAL-REFEX>
		</REFERENCE>
		<STRING> is also sometimes referred to as &quot;Achiktash&quot;. </STRING>
		<REFERENCE ID="5" SEMCAT="mountain" SYNCAT="np-subj">
			<ORIGINAL-REFEX>
				<REFEX CASE="nominative" EMPHATIC="no" HEAD="pronoun" TYPE="pronoun">It</REFEX>
			</ORIGINAL-REFEX>
		</REFERENCE>
		<STRING> was discovered in 1871 and originally named after Konstantin Kaufman.</STRING>
	</PARAGRAPH>
</TEXT>
