<?xml version="1.0" ?>
<TEXT ID="488">
	<TITLE>Mount Meru (Tanzania)</TITLE>
	<PARAGRAPH ID="1">
		<REFERENCE ID="1" SEMCAT="mountain" SYNCAT="np-subj">
			<ORIGINAL-REFEX>
				<REFEX CASE="plain" EMPHATIC="no" HEAD="nominal" TYPE="name">Mount Meru</REFEX>
			</ORIGINAL-REFEX>
		</REFERENCE>
		<STRING> is an active volcano located 70 kilometres (44 miles) west of Mount Kilimanjaro. </STRING>
		<REFERENCE ID="2" SEMCAT="mountain" SYNCAT="np-subj">
			<ORIGINAL-REFEX>
				<REFEX CASE="nominative" EMPHATIC="no" HEAD="pronoun" TYPE="pronoun">It</REFEX>
			</ORIGINAL-REFEX>
		</REFERENCE>
		<STRING> reaches 4,566 metres (14,980 feet) in height but </STRING>
		<REFERENCE ID="3" SEMCAT="mountain" SYNCAT="np-subj">
			<ORIGINAL-REFEX>
				<REFEX CASE="" EMPHATIC="" HEAD="" TYPE="empty">_</REFEX>
			</ORIGINAL-REFEX>
		</REFERENCE>
		<STRING> has lost much of </STRING>
		<REFERENCE ID="4" SEMCAT="mountain" SYNCAT="subj-det">
			<ORIGINAL-REFEX>
				<REFEX CASE="genitive" EMPHATIC="no" HEAD="pronoun" TYPE="pronoun">its</REFEX>
			</ORIGINAL-REFEX>
		</REFERENCE>
		<STRING> bulk due to an eastward volcanic blast about 8,000 years ago, similar to the 1980 eruption of Mount St. Helens in Washington. </STRING>
		<REFERENCE ID="5" SEMCAT="mountain" SYNCAT="np-subj">
			<ORIGINAL-REFEX>
				<REFEX CASE="plain" EMPHATIC="no" HEAD="nominal" TYPE="name">Mount Meru</REFEX>
			</ORIGINAL-REFEX>
		</REFERENCE>
		<STRING> most recently had a minor eruption about a century ago. The several small cones and craters seen in the vicinity probably reflect numerous episodes of volcanic activity.</STRING>
	</PARAGRAPH>
	<PARAGRAPH ID="2">
		<REFERENCE ID="6" SEMCAT="mountain" SYNCAT="np-subj">
			<ORIGINAL-REFEX>
				<REFEX CASE="plain" EMPHATIC="no" HEAD="nominal" TYPE="name">Mount Meru</REFEX>
			</ORIGINAL-REFEX>
		</REFERENCE>
		<STRING> is the topographic centerpiece of Arusha National Park. </STRING>
		<REFERENCE ID="7" SEMCAT="mountain" SYNCAT="subj-det">
			<ORIGINAL-REFEX>
				<REFEX CASE="genitive" EMPHATIC="no" HEAD="pronoun" TYPE="pronoun">Its</REFEX>
			</ORIGINAL-REFEX>
		</REFERENCE>
		<STRING> fertile slopes rise above the surrounding savanna and support a forest that hosts diverse wildlife, including nearly 400 species of birds, and also monkeys and leopards.</STRING>
	</PARAGRAPH>
	<PARAGRAPH ID="3">
		<STRING>At the summit in 2006, one can find a 2-m-high flag of Tanzania in metal and also a milestone in concrete with &quot;Socialist Peak 4562.13M&quot; written.</STRING>
	</PARAGRAPH>
</TEXT>
