<?xml version="1.0" ?>
<TEXT ID="841">
	<TITLE>Skyang Kangri</TITLE>
	<PARAGRAPH ID="1">
		<REFERENCE ID="1" SEMCAT="mountain" SYNCAT="np-subj">
			<ORIGINAL-REFEX>
				<REFEX CASE="plain" EMPHATIC="no" HEAD="nominal" TYPE="name">Skyang Kangri</REFEX>
			</ORIGINAL-REFEX>
		</REFERENCE>
		<STRING>, or Staircase Peak, is a high peak of the Baltoro Muztagh, a subrange of the Karakoram range. </STRING>
		<REFERENCE ID="2" SEMCAT="mountain" SYNCAT="np-subj">
			<ORIGINAL-REFEX>
				<REFEX CASE="nominative" EMPHATIC="no" HEAD="pronoun" TYPE="pronoun">It</REFEX>
			</ORIGINAL-REFEX>
		</REFERENCE>
		<STRING> lies on the Pakistan-China border, about 7km northeast of K2, the world's second-highest mountain. The name &quot;Staircase Peak&quot; refers to the East Ridge, which resembles a giant staircase with five steps.</STRING>
	</PARAGRAPH>
	<PARAGRAPH ID="2">
		<REFERENCE ID="3" SEMCAT="mountain" SYNCAT="np-subj">
			<ORIGINAL-REFEX>
				<REFEX CASE="plain" EMPHATIC="no" HEAD="nominal" TYPE="name">Skyang Kangri</REFEX>
			</ORIGINAL-REFEX>
		</REFERENCE>
		<STRING> was first attempted by the party of renowned climber and explorer Luigi Amadeo di Savoia, the Duke of the Abruzzi, in 1909, during an expedition to K2. They attempted the East Ridge, as did a subsequent failed attempt in 1975, in which one climber died and one had to be evacuated by helicopter. The first ascent was made in 1976 by a Japanese expedition, climbing the East Ridge without major incident.</STRING>
	</PARAGRAPH>
	<PARAGRAPH ID="3">
		<STRING>In 1980, well-known American climbers Jeff Lowe and Michael Kennedy attempted the West Face of </STRING>
		<REFERENCE ID="4" SEMCAT="mountain" SYNCAT="np-obj">
			<ORIGINAL-REFEX>
				<REFEX CASE="plain" EMPHATIC="no" HEAD="nominal" TYPE="name">Skyang Kangri</REFEX>
			</ORIGINAL-REFEX>
		</REFERENCE>
		<STRING>, but reached only about 7,070 metres. According to the Index, there have been no subsequent attempts on </STRING>
		<REFERENCE ID="5" SEMCAT="mountain" SYNCAT="np-obj">
			<ORIGINAL-REFEX>
				<REFEX CASE="plain" EMPHATIC="no" HEAD="nominal" TYPE="description">the mountain</REFEX>
			</ORIGINAL-REFEX>
		</REFERENCE>
		<STRING>.</STRING>
	</PARAGRAPH>
</TEXT>
