<?xml version="1.0" ?>
<TEXT ID="1165">
	<TITLE>Sarajevo</TITLE>
	<PARAGRAPH ID="1">
		<SENTENCE ID="1.1">
			<REFERENCE ID="1" PARAGRAPH-POSITION="1" PARAGRAPH-RECENCY="0" SEMCAT="city" SENTENCE-POSITION="1" SENTENCE-RECENCY="0" SYNCAT="np-subj">
				<ORIGINAL-REFEX>
					<REFEX CASE="plain" EMPHATIC="no" HEAD="nominal" TYPE="name">Sarajevo </REFEX>
				</ORIGINAL-REFEX>
			</REFERENCE>
			<STRING>(Cyrillic: Сарајево; [IPA: sa'rajɛʋɔ], in English usually IPA: ˌsærəˈjeɪvoʊ) is the capital city and largest urban center of Bosnia and Herzegovina, with an estimated population of 308,558 (as of 2005).</STRING>
		</SENTENCE>
		<SENTENCE ID="1.2">
			<REFERENCE ID="2" PARAGRAPH-POSITION="32" PARAGRAPH-RECENCY="31" SEMCAT="city" SENTENCE-POSITION="1" SENTENCE-RECENCY="0" SYNCAT="np-subj">
				<ORIGINAL-REFEX>
					<REFEX CASE="nominative" EMPHATIC="no" HEAD="pronoun" TYPE="pronoun">It</REFEX>
				</ORIGINAL-REFEX>
			</REFERENCE>
			<STRING> is also the capital of the Federation of Bosnia and Herzegovina entity, and the de jure capital of the Republika Srpska entity, as well as the center of the Sarajevo Canton.</STRING>
		</SENTENCE>
		<SENTENCE ID="1.3">
			<REFERENCE ID="3" PARAGRAPH-POSITION="64" PARAGRAPH-RECENCY="32" SEMCAT="city" SENTENCE-POSITION="1" SENTENCE-RECENCY="0" SYNCAT="np-subj">
				<ORIGINAL-REFEX>
					<REFEX CASE="plain" EMPHATIC="no" HEAD="nominal" TYPE="name">Sarajevo</REFEX>
				</ORIGINAL-REFEX>
			</REFERENCE>
			<STRING> is located in the Sarajevo valley of Bosnia proper, surrounded by the Dinaric Alps and situated around the Miljacka river.</STRING>
		</SENTENCE>
		<SENTENCE ID="1.4">
			<REFERENCE ID="4" PARAGRAPH-POSITION="85" PARAGRAPH-RECENCY="21" SEMCAT="city" SENTENCE-POSITION="1" SENTENCE-RECENCY="0" SYNCAT="np-subj">
				<ORIGINAL-REFEX>
					<REFEX CASE="plain" EMPHATIC="no" HEAD="nominal" TYPE="description">The city</REFEX>
				</ORIGINAL-REFEX>
			</REFERENCE>
			<STRING> is famous for  </STRING>
			<REFERENCE ID="5" PARAGRAPH-POSITION="89" PARAGRAPH-RECENCY="4" SEMCAT="city" SENTENCE-POSITION="5" SENTENCE-RECENCY="4" SYNCAT="subj-det">
				<ORIGINAL-REFEX>
					<REFEX CASE="genitive" EMPHATIC="no" HEAD="pronoun" TYPE="pronoun">its</REFEX>
				</ORIGINAL-REFEX>
			</REFERENCE>
			<STRING> traditional religious diversity, with adherents of Islam, Catholicism, Orthodoxy, and Judaism peacefully coexisting there for centuries. </STRING>
		</SENTENCE>
	</PARAGRAPH>
	<PARAGRAPH ID="2">
		<SENTENCE ID="2.1">
			<STRING>Although settlement in the area stretches back to prehistoric times,  </STRING>
			<REFERENCE ID="6" PARAGRAPH-POSITION="11" PARAGRAPH-RECENCY="0" SEMCAT="city" SENTENCE-POSITION="11" SENTENCE-RECENCY="0" SYNCAT="np-subj">
				<ORIGINAL-REFEX>
					<REFEX CASE="plain" EMPHATIC="no" HEAD="nominal" TYPE="description">the modern city</REFEX>
				</ORIGINAL-REFEX>
			</REFERENCE>
			<STRING> arose as an Ottoman stronghold in the 15th century.</STRING>
		</SENTENCE>
		<SENTENCE ID="2.2">
			<REFERENCE ID="7" PARAGRAPH-POSITION="21" PARAGRAPH-RECENCY="10" SEMCAT="city" SENTENCE-POSITION="1" SENTENCE-RECENCY="0" SYNCAT="np-subj">
				<ORIGINAL-REFEX>
					<REFEX CASE="plain" EMPHATIC="no" HEAD="nominal" TYPE="name">Sarajevo</REFEX>
				</ORIGINAL-REFEX>
			</REFERENCE>
			<STRING> has attracted international attention several times throughout  </STRING>
			<REFERENCE ID="8" PARAGRAPH-POSITION="29" PARAGRAPH-RECENCY="8" SEMCAT="city" SENTENCE-POSITION="9" SENTENCE-RECENCY="8" SYNCAT="subj-det">
				<ORIGINAL-REFEX>
					<REFEX CASE="genitive" EMPHATIC="no" HEAD="pronoun" TYPE="pronoun">its</REFEX>
				</ORIGINAL-REFEX>
			</REFERENCE>
			<STRING> history: In 1914  </STRING>
			<REFERENCE ID="9" PARAGRAPH-POSITION="33" PARAGRAPH-RECENCY="4" SEMCAT="city" SENTENCE-POSITION="13" SENTENCE-RECENCY="4" SYNCAT="np-subj">
				<ORIGINAL-REFEX>
					<REFEX CASE="nominative" EMPHATIC="no" HEAD="pronoun" TYPE="pronoun">it</REFEX>
				</ORIGINAL-REFEX>
			</REFERENCE>
			<STRING> was the site of the assassination that sparked World War I, while seventy years later  </STRING>
			<REFERENCE ID="10" PARAGRAPH-POSITION="49" PARAGRAPH-RECENCY="16" SEMCAT="city" SENTENCE-POSITION="29" SENTENCE-RECENCY="16" SYNCAT="np-subj">
				<ORIGINAL-REFEX>
					<REFEX CASE="nominative" EMPHATIC="no" HEAD="pronoun" TYPE="pronoun">it</REFEX>
				</ORIGINAL-REFEX>
			</REFERENCE>
			<STRING> became the host city of the 1984 Winter Olympics.</STRING>
		</SENTENCE>
		<SENTENCE ID="2.3">
			<STRING>More recently,  </STRING>
			<REFERENCE ID="11" PARAGRAPH-POSITION="61" PARAGRAPH-RECENCY="12" SEMCAT="city" SENTENCE-POSITION="3" SENTENCE-RECENCY="0" SYNCAT="np-subj">
				<ORIGINAL-REFEX>
					<REFEX CASE="plain" EMPHATIC="no" HEAD="nominal" TYPE="name">Sarajevo</REFEX>
				</ORIGINAL-REFEX>
			</REFERENCE>
			<STRING> underwent the longest siege in modern military history during the Bosnian war.</STRING>
		</SENTENCE>
		<SENTENCE ID="2.4">
			<STRING>Today  </STRING>
			<REFERENCE ID="12" PARAGRAPH-POSITION="75" PARAGRAPH-RECENCY="14" SEMCAT="city" SENTENCE-POSITION="2" SENTENCE-RECENCY="0" SYNCAT="np-subj">
				<ORIGINAL-REFEX>
					<REFEX CASE="plain" EMPHATIC="no" HEAD="nominal" TYPE="description">the city</REFEX>
				</ORIGINAL-REFEX>
			</REFERENCE>
			<STRING> is recovering and adjusting to a post-war reality, as a major center of culture and economic development in Bosnia and Herzegovina. </STRING>
		</SENTENCE>
	</PARAGRAPH>
</TEXT>
