<?xml version="1.0" encoding="utf-8"?>
<!DOCTYPE TEXT SYSTEM "reg08-grec.dtd">
<TEXT ID="1270">
<TITLE>French Polynesia</TITLE>

<PARAGRAPH>
<REF ID="1270.1" SEMCAT="country" SYNCAT="np-subj">
<REFEX REG08-TYPE="name" EMPHATIC="no" HEAD="nominal" CASE="plain">French Polynesia</REFEX>
<ALT-REFEX>
<REFEX REG08-TYPE="name" EMPHATIC="no" HEAD="nominal" CASE="plain">French Polynesia</REFEX>
<REFEX REG08-TYPE="name" EMPHATIC="yes" HEAD="nominal" CASE="plain">French Polynesia itself</REFEX>
<REFEX REG08-TYPE="empty">_</REFEX>
<REFEX REG08-TYPE="pronoun" EMPHATIC="no" HEAD="pronoun" CASE="nominative">it</REFEX>
<REFEX REG08-TYPE="pronoun" EMPHATIC="yes" HEAD="pronoun" CASE="nominative">it itself</REFEX>
<REFEX REG08-TYPE="pronoun" EMPHATIC="no" HEAD="rel-pron" CASE="nominative">that</REFEX>
<REFEX REG08-TYPE="pronoun" EMPHATIC="yes" HEAD="rel-pron" CASE="nominative">that itself</REFEX>
<REFEX REG08-TYPE="common" EMPHATIC="no" HEAD="nominal" CASE="plain">the country</REFEX>
<REFEX REG08-TYPE="common" EMPHATIC="yes" HEAD="nominal" CASE="plain">the country itself</REFEX>
<REFEX REG08-TYPE="pronoun" EMPHATIC="no" HEAD="rel-pron" CASE="nominative">which</REFEX>
<REFEX REG08-TYPE="pronoun" EMPHATIC="yes" HEAD="rel-pron" CASE="nominative">which itself</REFEX>
</ALT-REFEX>
</REF>
 (French: Polynésie française, Tahitian: Pōrīnetia Farāni) is a French "overseas collectivity" (French: collectivité d'outre-mer, or COM) with the particular designation of "overseas country" (French: pays d'outre-mer, or POM) in the southern Pacific Ocean. 
<REF ID="1270.2" SEMCAT="country" SYNCAT="np-subj">
<REFEX REG08-TYPE="pronoun" EMPHATIC="no" HEAD="pronoun" CASE="nominative">It</REFEX>
<ALT-REFEX>
<REFEX REG08-TYPE="name" EMPHATIC="no" HEAD="nominal" CASE="plain">French Polynesia</REFEX>
<REFEX REG08-TYPE="name" EMPHATIC="yes" HEAD="nominal" CASE="plain">French Polynesia itself</REFEX>
<REFEX REG08-TYPE="empty">_</REFEX>
<REFEX REG08-TYPE="pronoun" EMPHATIC="no" HEAD="pronoun" CASE="nominative">it</REFEX>
<REFEX REG08-TYPE="pronoun" EMPHATIC="yes" HEAD="pronoun" CASE="nominative">it itself</REFEX>
<REFEX REG08-TYPE="pronoun" EMPHATIC="no" HEAD="rel-pron" CASE="nominative">that</REFEX>
<REFEX REG08-TYPE="pronoun" EMPHATIC="yes" HEAD="rel-pron" CASE="nominative">that itself</REFEX>
<REFEX REG08-TYPE="common" EMPHATIC="no" HEAD="nominal" CASE="plain">the country</REFEX>
<REFEX REG08-TYPE="common" EMPHATIC="yes" HEAD="nominal" CASE="plain">the country itself</REFEX>
<REFEX REG08-TYPE="pronoun" EMPHATIC="no" HEAD="rel-pron" CASE="nominative">which</REFEX>
<REFEX REG08-TYPE="pronoun" EMPHATIC="yes" HEAD="rel-pron" CASE="nominative">which itself</REFEX>
</ALT-REFEX>
</REF>
 is made up of several groups of Polynesian islands, the most famous island being Tahiti in the Society Islands group, which is also the most populous island, and the seat of the capital of the territory (Papeete). Although not an integral part of 
<REF ID="1270.3" SEMCAT="country" SYNCAT="subj-det">
<REFEX REG08-TYPE="pronoun" EMPHATIC="no" HEAD="pronoun" CASE="genitive">its</REFEX>
<ALT-REFEX>
<REFEX REG08-TYPE="name" EMPHATIC="no" HEAD="nominal" CASE="genitive">French Polynesia's</REFEX>
<REFEX REG08-TYPE="pronoun" EMPHATIC="no" HEAD="pronoun" CASE="genitive">its</REFEX>
<REFEX REG08-TYPE="common" EMPHATIC="no" HEAD="nominal" CASE="genitive">the country's</REFEX>
<REFEX REG08-TYPE="pronoun" EMPHATIC="no" HEAD="rel-pron" CASE="genitive">whose</REFEX>
</ALT-REFEX>
</REF>
 territory, Clipperton Island is administered from 
<REF ID="1270.4" SEMCAT="country" SYNCAT="np-obj">
<REFEX REG08-TYPE="name" EMPHATIC="no" HEAD="nominal" CASE="plain">French Polynesia</REFEX>
<ALT-REFEX>
<REFEX REG08-TYPE="name" EMPHATIC="no" HEAD="nominal" CASE="plain">French Polynesia</REFEX>
<REFEX REG08-TYPE="name" EMPHATIC="yes" HEAD="nominal" CASE="plain">French Polynesia itself</REFEX>
<REFEX REG08-TYPE="pronoun" EMPHATIC="no" HEAD="pronoun" CASE="accusative">it</REFEX>
<REFEX REG08-TYPE="pronoun" EMPHATIC="yes" HEAD="pronoun" CASE="accusative">it itself</REFEX>
<REFEX REG08-TYPE="pronoun" EMPHATIC="no" HEAD="pronoun" CASE="accusative">itself</REFEX>
<REFEX REG08-TYPE="common" EMPHATIC="no" HEAD="nominal" CASE="plain">the country</REFEX>
<REFEX REG08-TYPE="common" EMPHATIC="yes" HEAD="nominal" CASE="plain">the country itself</REFEX>
</ALT-REFEX>
</REF>
.</PARAGRAPH>
</TEXT>
