<?xml version="1.0" ?>
<TEXT ID="952">
	<TITLE>India</TITLE>
	<PARAGRAPH ID="1">
		<SENTENCE ID="1.1">
			<REFERENCE ID="1" SEMCAT="country" SYNCAT="np-subj">
				<ORIGINAL-REFEX>
					<REFEX CASE="plain" EMPHATIC="no" HEAD="nominal" TYPE="name">India</REFEX>
				</ORIGINAL-REFEX>
			</REFERENCE>
			<STRING> (Devanagari: भारत Bhārat), officially the Republic of India (Bhārata Gaṇarājya), is a country in South Asia.</STRING>
		</SENTENCE>
		<SENTENCE ID="1.2">
			<REFERENCE ID="2" SEMCAT="country" SYNCAT="np-subj">
				<ORIGINAL-REFEX>
					<REFEX CASE="nominative" EMPHATIC="no" HEAD="pronoun" TYPE="pronoun">It</REFEX>
				</ORIGINAL-REFEX>
			</REFERENCE>
			<STRING> is the seventh-largest country by geographical area, the second most populous country, and the most populous liberal democracy in the world.</STRING>
		</SENTENCE>
		<SENTENCE ID="1.3">
			<REFERENCE ID="3" SEMCAT="country" SYNCAT="np-subj">
				<ORIGINAL-REFEX>
					<REFEX CASE="plain" EMPHATIC="no" HEAD="nominal" TYPE="name">India</REFEX>
				</ORIGINAL-REFEX>
			</REFERENCE>
			<STRING> has a coastline of over seven thousand kilometres which is bounded by the Indian Ocean on the south, the Arabian Sea on the west, and the Bay of Bengal on the east.</STRING>
		</SENTENCE>
		<SENTENCE ID="1.4">
			<REFERENCE ID="4" SEMCAT="country" SYNCAT="np-subj">
				<ORIGINAL-REFEX>
					<REFEX CASE="plain" EMPHATIC="no" HEAD="nominal" TYPE="name">India</REFEX>
				</ORIGINAL-REFEX>
			</REFERENCE>
			<STRING> borders Afghanistan and Pakistan to the west; China, Nepal and Bhutan to the north-east; and Bangladesh and Myanmar to the east.</STRING>
		</SENTENCE>
		<SENTENCE ID="1.5">
			<REFERENCE ID="5" SEMCAT="country" SYNCAT="np-subj">
				<ORIGINAL-REFEX>
					<REFEX CASE="plain" EMPHATIC="no" HEAD="nominal" TYPE="name">India</REFEX>
				</ORIGINAL-REFEX>
			</REFERENCE>
			<STRING> is in the vicinity of the Indian Ocean nations of Sri Lanka, Maldives, Indonesia and Thailand. </STRING>
		</SENTENCE>
	</PARAGRAPH>
	<PARAGRAPH ID="2">
		<SENTENCE ID="2.1">
			<STRING>The first urban civilization on the Indian subcontinent arose around 3300 BCE in the Indus river valley.</STRING>
		</SENTENCE>
		<SENTENCE ID="2.2">
			<REFERENCE ID="6" SEMCAT="country" SYNCAT="np-subj">
				<ORIGINAL-REFEX>
					<REFEX CASE="plain" EMPHATIC="no" HEAD="nominal" TYPE="name">India</REFEX>
				</ORIGINAL-REFEX>
			</REFERENCE>
			<STRING> subsequently became a hub of ancient trade routes, the seat of vast empires, and a center of cultural innovation and synthesis, whose diverse achievements included the decimal number system,the Buddhist cave monuments at Ajanta, and the Taj Mahal.</STRING>
		</SENTENCE>
		<SENTENCE ID="2.3">
			<STRING>Four of the world's major religions, Hinduism, Buddhism, Jainism and Sikhism originated in  </STRING>
			<REFERENCE ID="7" SEMCAT="country" SYNCAT="np-obj">
				<ORIGINAL-REFEX>
					<REFEX CASE="plain" EMPHATIC="no" HEAD="nominal" TYPE="name">India</REFEX>
				</ORIGINAL-REFEX>
			</REFERENCE>
			<STRING>, while Islam, Christianity, Judaism and Zoroastrianism, arrived in the first millennium CE and played an influential role in the formation of the variegated culture of  </STRING>
			<REFERENCE ID="8" SEMCAT="country" SYNCAT="np-obj">
				<ORIGINAL-REFEX>
					<REFEX CASE="plain" EMPHATIC="no" HEAD="nominal" TYPE="name">India</REFEX>
				</ORIGINAL-REFEX>
			</REFERENCE>
			<STRING>.</STRING>
		</SENTENCE>
		<SENTENCE ID="2.4">
			<STRING>In addition, through the transmission of Buddhism and Hinduism,  </STRING>
			<REFERENCE ID="9" SEMCAT="country" SYNCAT="np-subj">
				<ORIGINAL-REFEX>
					<REFEX CASE="plain" EMPHATIC="no" HEAD="nominal" TYPE="name">India</REFEX>
				</ORIGINAL-REFEX>
			</REFERENCE>
			<STRING> notably influenced the cultures of South Asia,South-east Asia,and East Asia. </STRING>
		</SENTENCE>
	</PARAGRAPH>
	<PARAGRAPH ID="3">
		<SENTENCE ID="3.1">
			<REFERENCE ID="10" SEMCAT="country" SYNCAT="np-subj">
				<ORIGINAL-REFEX>
					<REFEX CASE="plain" EMPHATIC="no" HEAD="nominal" TYPE="name">India</REFEX>
				</ORIGINAL-REFEX>
			</REFERENCE>
			<STRING> emerged as a modern democratic nation-state in 1947 after a struggle for independence that was characterized by the first large-scale use of nonviolent resistance and civil disobedience as a means of social protest.</STRING>
		</SENTENCE>
		<SENTENCE ID="3.2">
			<REFERENCE ID="11" SEMCAT="country" SYNCAT="np-subj">
				<ORIGINAL-REFEX>
					<REFEX CASE="nominative" EMPHATIC="no" HEAD="pronoun" TYPE="pronoun">It</REFEX>
				</ORIGINAL-REFEX>
			</REFERENCE>
			<STRING> became a republic in 1950, with the completion of a constitution that guaranteed &quot;liberty of thought, expression, belief, faith, and worship.&quot;</STRING>
		</SENTENCE>
		<SENTENCE ID="3.3">
			<REFERENCE ID="12" SEMCAT="country" SYNCAT="np-subj">
				<ORIGINAL-REFEX>
					<REFEX CASE="plain" EMPHATIC="no" HEAD="nominal" TYPE="name">Modern India</REFEX>
				</ORIGINAL-REFEX>
			</REFERENCE>
			<STRING> is a large and complex country that defies easy characterization.</STRING>
		</SENTENCE>
		<SENTENCE ID="3.4">
			<STRING>On the one hand,  </STRING>
			<REFERENCE ID="13" SEMCAT="country" SYNCAT="np-subj">
				<ORIGINAL-REFEX>
					<REFEX CASE="nominative" EMPHATIC="no" HEAD="pronoun" TYPE="pronoun">it</REFEX>
				</ORIGINAL-REFEX>
			</REFERENCE>
			<STRING> is now the fourth largest economy (PPP) in the world and the second fastest growing economy,having made rapid economic progress in the last ten years, especially in the field of information technology.</STRING>
		</SENTENCE>
		<SENTENCE ID="3.5">
			<REFERENCE ID="14" SEMCAT="country" SYNCAT="np-subj">
				<ORIGINAL-REFEX>
					<REFEX CASE="nominative" EMPHATIC="no" HEAD="pronoun" TYPE="pronoun">It</REFEX>
				</ORIGINAL-REFEX>
			</REFERENCE>
			<STRING> has the second largest agricultural output of any country in the world;  </STRING>
			<REFERENCE ID="15" SEMCAT="country" SYNCAT="np-subj">
				<ORIGINAL-REFEX>
					<REFEX CASE="nominative" EMPHATIC="no" HEAD="pronoun" TYPE="pronoun">it</REFEX>
				</ORIGINAL-REFEX>
			</REFERENCE>
			<STRING> is a declared nuclear deterrent state,with an active space program; and  </STRING>
			<REFERENCE ID="16" SEMCAT="country" SYNCAT="np-subj">
				<ORIGINAL-REFEX>
					<REFEX CASE="nominative" EMPHATIC="no" HEAD="pronoun" TYPE="pronoun">it</REFEX>
				</ORIGINAL-REFEX>
			</REFERENCE>
			<STRING> is sometimes spoken of as an emerging superpower.On the other hand, despite these gains,  </STRING>
			<REFERENCE ID="17" SEMCAT="country" SYNCAT="np-subj">
				<ORIGINAL-REFEX>
					<REFEX CASE="plain" EMPHATIC="no" HEAD="nominal" TYPE="name">India</REFEX>
				</ORIGINAL-REFEX>
			</REFERENCE>
			<STRING> battles endemic poverty and uneven development.</STRING>
		</SENTENCE>
		<SENTENCE ID="3.6">
			<REFERENCE ID="18" SEMCAT="country" SYNCAT="np-subj">
				<ORIGINAL-REFEX>
					<REFEX CASE="nominative" EMPHATIC="no" HEAD="pronoun" TYPE="pronoun">It</REFEX>
				</ORIGINAL-REFEX>
			</REFERENCE>
			<STRING> ranks 122nd in per capita income among the nations of the world, with four-fifths of  </STRING>
			<REFERENCE ID="19" SEMCAT="country" SYNCAT="subj-det">
				<ORIGINAL-REFEX>
					<REFEX CASE="genitive" EMPHATIC="no" HEAD="pronoun" TYPE="pronoun">its</REFEX>
				</ORIGINAL-REFEX>
			</REFERENCE>
			<STRING> population living on less than $2 a day.</STRING>
		</SENTENCE>
		<SENTENCE ID="3.7">
			<REFERENCE ID="20" SEMCAT="country" SYNCAT="np-subj">
				<ORIGINAL-REFEX>
					<REFEX CASE="plain" EMPHATIC="no" HEAD="nominal" TYPE="name">India</REFEX>
				</ORIGINAL-REFEX>
			</REFERENCE>
			<STRING> also ranks 126th in the 2006 UN human development index and, according to the FAO,  </STRING>
			<REFERENCE ID="21" SEMCAT="country" SYNCAT="np-subj">
				<ORIGINAL-REFEX>
					<REFEX CASE="" EMPHATIC="" HEAD="" TYPE="empty">_</REFEX>
				</ORIGINAL-REFEX>
			</REFERENCE>
			<STRING> has the largest number of undernourished people of any country in the world,which, at 212 million, is a full one-fifth of the population.However,  </STRING>
			<REFERENCE ID="22" SEMCAT="country" SYNCAT="subj-det">
				<ORIGINAL-REFEX>
					<REFEX CASE="genitive" EMPHATIC="no" HEAD="nominal" TYPE="name">India's</REFEX>
				</ORIGINAL-REFEX>
			</REFERENCE>
			<STRING> overall prognosis is now much improved: with  </STRING>
			<REFERENCE ID="23" SEMCAT="country" SYNCAT="subj-det">
				<ORIGINAL-REFEX>
					<REFEX CASE="genitive" EMPHATIC="no" HEAD="pronoun" TYPE="pronoun">its</REFEX>
				</ORIGINAL-REFEX>
			</REFERENCE>
			<STRING> high rate of growth,  </STRING>
			<REFERENCE ID="24" SEMCAT="country" SYNCAT="subj-det">
				<ORIGINAL-REFEX>
					<REFEX CASE="genitive" EMPHATIC="no" HEAD="pronoun" TYPE="pronoun">its</REFEX>
				</ORIGINAL-REFEX>
			</REFERENCE>
			<STRING> standard of living is expected to rise sharply in the 21st century. </STRING>
		</SENTENCE>
	</PARAGRAPH>
</TEXT>
